harvesters_util/__init__.py
harvesters_util/_version.py
harvesters_util/logging.py
harvesters_util/pfnc.py
harvesters_util-0.1.0.dist-info/LICENSE.txt
harvesters_util-0.1.0.dist-info/METADATA
harvesters_util-0.1.0.dist-info/RECORD
harvesters_util-0.1.0.dist-info/WHEEL
harvesters_util-0.1.0.dist-info/top_level.txt
