Metadata-Version: 2.1
Name: harvesters-util
Version: 0.1.0
Summary: Image acquisition & visualization library with Python (Maintained by the official GenICam committee)
Home-page: https://github.com/genicam/harvesters_util
Author: The GenICam Committee
Author-email: genicam@list.stemmer-imaging.com
License: Apache Software License V2.0
Download-URL: https://pypi.org/project/harvesters_util/
Platform: any
Classifier: Development Status :: 3 - Alpha
Classifier: Intended Audience :: Science/Research
Classifier: Intended Audience :: Education
Classifier: Intended Audience :: Developers
Classifier: License :: OSI Approved :: Apache Software License
Classifier: Operating System :: MacOS :: MacOS X
Classifier: Operating System :: Microsoft :: Windows
Classifier: Operating System :: POSIX
Classifier: Programming Language :: Python :: 3.4
Classifier: Programming Language :: Python :: 3.5
Classifier: Programming Language :: Python :: 3.6
Provides: harvesters_util
